{"devices": {"1": {"data": {"device_name": "Device1", "managed_by_user_id": "one@mci.edu", "is_active": true, "reservation_queue": []}}, "2": {"data": {"device_name": "Device2", "managed_by_user_id": "two@mci.edu", "is_active": true, "reservation_queue": []}}, "3": {"data": {"device_name": "Device3", "managed_by_user_id": "three@mci.edu", "is_active": true, "reservation_queue": []}}, "4": {"data": {"device_name": "Device4", "managed_by_user_id": "four@mci.edu", "is_active": true, "reservation_queue": []}}}, "users": {"2": {"id": "bs7677@mci4me.at", "name": "Sebastian Bachlechner", "email": "bs7677@mci4me.at", "location": "IV", "job": "Student"}, "3": {"id": "hn1233@mci4me.at", "name": "Noel Hack", "email": "hn1233@mci4me.at", "location": "IV", "job": "Student"}, "4": {"id": "st3542@mci4me.at", "name": "Tobias Stummer", "email": "st3542@mci4me.at", "location": "I", "job": "Student"}}}